feltorutilities/__init__.py
feltorutilities-0.0.0.dist-info/licenses/LICENSE
feltorutilities-0.0.0.dist-info/METADATA
feltorutilities-0.0.0.dist-info/WHEEL
feltorutilities-0.0.0.dist-info/top_level.txt
feltorutilities-0.0.0.dist-info/RECORD
