Metadata-Version: 2.4
Name: feltorutilities
Version: 0.0.0
Summary: Utilities for the setup and analysis of 3d feltor simulations
Author-email: Matthias Wiesenberger <mattwi@fysik.dtu.dk>
License: MIT License
Project-URL: Source, https://github.com/mwiesenberger/feltorutilities
Project-URL: Tracker, https://github.com/mwiesenberger/feltorutilities/issues
Classifier: Programming Language :: Python :: 3
Classifier: License :: OSI Approved :: MIT License
Classifier: Operating System :: OS Independent
Classifier: Topic :: Software Development :: Libraries
Classifier: Topic :: Scientific/Engineering
Classifier: Topic :: Utilities
Requires-Python: >=3.10
License-File: LICENSE
Requires-Dist: scipy>=1.10.0
Requires-Dist: numpy>=1.24.0
Provides-Extra: test
Requires-Dist: pytest; extra == "test"
Provides-Extra: lint
Requires-Dist: ruff; extra == "lint"
Provides-Extra: jupyter
Requires-Dist: jupyterlab>=4.3.5; extra == "jupyter"
Requires-Dist: matplotlib>=3.10.1; extra == "jupyter"
Requires-Dist: netcdf4>=1.7.2; extra == "jupyter"
Requires-Dist: numpy>=2.2.3; extra == "jupyter"
Requires-Dist: scipy>=1.15.2; extra == "jupyter"
Requires-Dist: simplesimdb>=1.1.1; extra == "jupyter"
Requires-Dist: magneticfielddb>=0.1.1; extra == "jupyter"
Dynamic: license-file
